tvcoint/__init__.py
tvcoint/bootstrap_tests.py
tvcoint/chebyshev.py
tvcoint/critical_values.py
tvcoint/tests.py
tvcoint/tv_vecm.py
tvcoint/utils.py
tvcoint/vecm.py
tvcoint-1.1.0.dist-info/licenses/LICENSE
tvcoint-1.1.0.dist-info/METADATA
tvcoint-1.1.0.dist-info/WHEEL
tvcoint-1.1.0.dist-info/top_level.txt
tvcoint-1.1.0.dist-info/RECORD
